<?xml version="1.0" encoding="utf-8" ?><dwsync><file name="banner.jpg" server="salusmodel.glg.msu.edu/public_html/" local="3474898830" remote="12071819062" /><file name="nav-bg.jpg" server="salusmodel.glg.msu.edu/public_html/" local="3474898830" remote="12071819062" /><file name="mid-repet.jpg" server="salusmodel.glg.msu.edu/public_html/" local="3474898830" remote="12071819062" /><file name="divider-1.jpg" server="salusmodel.glg.msu.edu/public_html/" local="3474898830" remote="12071819062" /><file name="bullet1.jpg" server="salusmodel.glg.msu.edu/public_html/" local="3474898830" remote="12071819062" /><file name="divider-2.jpg" server="salusmodel.glg.msu.edu/public_html/" local="3474898830" remote="12071819062" /><file name="right-grey.jpg" server="salusmodel.glg.msu.edu/public_html/" local="3474898830" remote="12071819062" /><file name="divider-4.jpg" server="salusmodel.glg.msu.edu/public_html/" local="3474898830" remote="12071819062" /><file name="bullet-2.jpg" server="salusmodel.glg.msu.edu/public_html/" local="3474898830" remote="12071819062" /><file name="divider-3.jpg" server="salusmodel.glg.msu.edu/public_html/" local="3474898830" remote="12071819062" /><file name="mid-bttm.jpg" server="salusmodel.glg.msu.edu/public_html/" local="3474898830" remote="12071819063" /><file name="footnote.gif" server="salusmodel.glg.msu.edu/public_html/" local="3474898830" remote="12071819063" /></dwsync>